pg_table_builder/__init__.py
pg_table_builder/exceptions.py
pg_table_builder/types.py
pg_table_builder-1.1.0.dist-info/LICENSE
pg_table_builder-1.1.0.dist-info/LICENSE.md
pg_table_builder-1.1.0.dist-info/METADATA
pg_table_builder-1.1.0.dist-info/WHEEL
pg_table_builder-1.1.0.dist-info/top_level.txt
pg_table_builder-1.1.0.dist-info/RECORD
