Metadata-Version: 2.1
Name: pg_table_builder
Version: 1.1.0
Summary: Table builder for postgresql
Home-page: https://github.com/byBenPuls/table-builder-pg
Author: Ben Puls
Author-email: discordben7@gmail.com
Project-URL: GitHub, https://github.com/byBenPuls/table-builder-pg
Keywords: postgresql
Classifier: Programming Language :: Python :: 3.11
Classifier: License :: OSI Approved :: MIT License
Classifier: Operating System :: OS Independent
Requires-Python: >=3.9
License-File: LICENSE
License-File: LICENSE.md
